nlpkm/__init__.py
nlpkm/main.py
nlpkm-0.0.1.dist-info/METADATA
nlpkm-0.0.1.dist-info/WHEEL
nlpkm-0.0.1.dist-info/top_level.txt
nlpkm-0.0.1.dist-info/RECORD
