Metadata-Version: 2.1
Name: nlpkm
Version: 0.0.1
Summary: NLP Packing Help 
Author: NeuralNine (Florian Dedov)
Author-email: jack2018@gmail.com
Keywords: python,video,stream,video stream,camera stream,sockets
Classifier: Development Status :: 1 - Planning
Classifier: Intended Audience :: Developers
Classifier: Programming Language :: Python :: 3
Classifier: Operating System :: Unix
Classifier: Operating System :: MacOS :: MacOS X
Classifier: Operating System :: Microsoft :: Windows
